odoo/addons/commission/README.rst
odoo/addons/commission/__init__.py
odoo/addons/commission/__manifest__.py
odoo/addons/commission/data/menuitem_data.xml
odoo/addons/commission/demo/commission_and_agent_demo.xml
odoo/addons/commission/i18n/commission.pot
odoo/addons/commission/i18n/es.po
odoo/addons/commission/i18n/it.po
odoo/addons/commission/i18n/ja.po
odoo/addons/commission/i18n/pt.po
odoo/addons/commission/i18n/pt_BR.po
odoo/addons/commission/i18n/tr.po
odoo/addons/commission/models/__init__.py
odoo/addons/commission/models/commission.py
odoo/addons/commission/models/commission_mixin.py
odoo/addons/commission/models/commission_settlement.py
odoo/addons/commission/models/product_template.py
odoo/addons/commission/models/res_partner.py
odoo/addons/commission/readme/CONFIGURE.md
odoo/addons/commission/readme/CONTRIBUTORS.md
odoo/addons/commission/readme/DESCRIPTION.md
odoo/addons/commission/readme/ROADMAP.md
odoo/addons/commission/readme/USAGE.md
odoo/addons/commission/reports/commission_settlement_report.xml
odoo/addons/commission/reports/gruoped_report_settlement_templates.xml
odoo/addons/commission/reports/report_settlement_templates.xml
odoo/addons/commission/security/commission_security.xml
odoo/addons/commission/security/ir.model.access.csv
odoo/addons/commission/static/description/icon.png
odoo/addons/commission/static/description/icon.svg
odoo/addons/commission/static/description/index.html
odoo/addons/commission/tests/__init__.py
odoo/addons/commission/tests/test_commission.py
odoo/addons/commission/views/commission_mixin_views.xml
odoo/addons/commission/views/commission_settlement_views.xml
odoo/addons/commission/views/commission_views.xml
odoo/addons/commission/views/product_template_views.xml
odoo/addons/commission/views/res_partner_views.xml
odoo/addons/commission/wizards/__init__.py
odoo/addons/commission/wizards/commission_make_settle.py
odoo/addons/commission/wizards/commission_make_settle_views.xml
odoo_addon_commission-17.0.1.1.2.2.dist-info/METADATA
odoo_addon_commission-17.0.1.1.2.2.dist-info/WHEEL
odoo_addon_commission-17.0.1.1.2.2.dist-info/top_level.txt
odoo_addon_commission-17.0.1.1.2.2.dist-info/RECORD
